eserialcall/__init__.py
eserialcall/py.typed
eserialcall-0.1.0.dist-info/METADATA
eserialcall-0.1.0.dist-info/WHEEL
eserialcall-0.1.0.dist-info/RECORD
