Metadata-Version: 2.1
Name: eserialcall
Version: 0.1.0
Summary: Python Call Serialization
Author: Erik Soma
Author-email: stillusingirc@gmail.com
Requires-Python: >=3.12,<4.0
Classifier: Programming Language :: Python :: 3
Classifier: Programming Language :: Python :: 3.12
